coreason_etl_pubmedabstracts/__init__.py
coreason_etl_pubmedabstracts/main.py
coreason_etl_pubmedabstracts/pipelines/__init__.py
coreason_etl_pubmedabstracts/pipelines/pubmed_pipeline.py
coreason_etl_pubmedabstracts/pipelines/xml_utils.py
coreason_etl_pubmedabstracts/utils/__init__.py
coreason_etl_pubmedabstracts/utils/logger.py
coreason_etl_pubmedabstracts-0.1.0.dist-info/METADATA
coreason_etl_pubmedabstracts-0.1.0.dist-info/WHEEL
coreason_etl_pubmedabstracts-0.1.0.dist-info/licenses/LICENSE
coreason_etl_pubmedabstracts-0.1.0.dist-info/licenses/NOTICE
coreason_etl_pubmedabstracts-0.1.0.dist-info/RECORD
