Metadata-Version: 2.4
Name: coreason-etl-pubmedabstracts
Version: 0.1.0
Summary: Fast, extensible Python ETL to maintain a local PubMed mirror
License: # The Prosperity Public License 3.0.0
License-File: LICENSE
License-File: NOTICE
Author: Gowtham A Rao
Author-email: gowtham.rao@coreason.ai
Requires-Python: >=3.11
Classifier: License :: Other/Proprietary License
Classifier: Programming Language :: Python :: 3.12
Classifier: Operating System :: OS Independent
Requires-Dist: dbt-postgres (>=1.10.0,<2.0.0)
Requires-Dist: dlt[duckdb] (>=1.20.0,<2.0.0)
Requires-Dist: fsspec (>=2025.12.0,<2026.0.0)
Requires-Dist: loguru (>=0.7.2,<0.8.0)
Requires-Dist: lxml (>=6.0.2,<7.0.0)
Requires-Dist: xmltodict (>=1.0.2,<2.0.0)
Project-URL: Documentation, https://github.com/CoReason-AI/coreason_etl_pubmedabstracts
Project-URL: Homepage, https://github.com/CoReason-AI/coreason_etl_pubmedabstracts
Project-URL: Repository, https://github.com/CoReason-AI/coreason_etl_pubmedabstracts
